continuous_futures/__init__.py
continuous_futures/continuous_futures.py
continuous_futures-0.0.1.dist-info/METADATA
continuous_futures-0.0.1.dist-info/WHEEL
continuous_futures-0.0.1.dist-info/licenses/LICENSE
continuous_futures-0.0.1.dist-info/RECORD
