Metadata-Version: 2.1
Name: continuous_futures
Version: 0.0.1
Summary: Converts single future contracts to a continuous contract (ratio back-adjusted)
Project-URL: Homepage, https://github.com/fxstr/continuous_futures
Project-URL: Bug Tracker, https://github.com/fxstr/continuous_futures/issues
Author-email: Felix Steiner <f@fxstr.com>
License-File: LICENSE
Classifier: License :: OSI Approved :: ISC License (ISCL)
Classifier: Operating System :: OS Independent
Classifier: Programming Language :: Python :: 3
Requires-Python: >=3.7
